fepydas/__init__.py
fepydas/constructors/Binner.py
fepydas/constructors/Plots.py
fepydas/constructors/__init__.py
fepydas/constructors/datareaders/Custom.py
fepydas/constructors/datareaders/FromLabview.py
fepydas/constructors/datareaders/Generic.py
fepydas/constructors/datareaders/Proprietary.py
fepydas/constructors/datareaders/__init__.py
fepydas/datatypes/Data.py
fepydas/datatypes/Dataset.py
fepydas/datatypes/__init__.py
fepydas/libs/__init__.py
fepydas/libs/fit_functions.py
fepydas/libs/sdtfile.py
fepydas/workers/ASCIIWriter.py
fepydas/workers/DirectoryLoader.py
fepydas/workers/Fit.py
fepydas/workers/__init__.py
fepydas-0.0.74.dist-info/METADATA
fepydas-0.0.74.dist-info/WHEEL
fepydas-0.0.74.dist-info/top_level.txt
fepydas-0.0.74.dist-info/RECORD
